adafruit_tlc59711.py
adafruit_circuitpython_tlc59711-2.0.18.dist-info/licenses/LICENSE
adafruit_circuitpython_tlc59711-2.0.18.dist-info/METADATA
adafruit_circuitpython_tlc59711-2.0.18.dist-info/WHEEL
adafruit_circuitpython_tlc59711-2.0.18.dist-info/top_level.txt
adafruit_circuitpython_tlc59711-2.0.18.dist-info/RECORD
