Metadata-Version: 2.4
Name: adafruit-circuitpython-tlc59711
Version: 2.0.18
Summary: CircuitPython library for TLC59711 16-bit 12 channel LED PWM driver.
Author-email: Adafruit Industries <circuitpython@adafruit.com>
License: MIT
Project-URL: Homepage, https://github.com/adafruit/Adafruit_CircuitPython_TLC59711
Keywords: adafruit,tlc59711,16-bit,12-channel,led,pwm,hardware,micropython,circuitpython
Classifier: Intended Audience :: Developers
Classifier: Topic :: Software Development :: Libraries
Classifier: Topic :: Software Development :: Embedded Systems
Classifier: Topic :: System :: Hardware
Classifier: License :: OSI Approved :: MIT License
Classifier: Programming Language :: Python :: 3
License-File: LICENSE
Requires-Dist: Adafruit-Blinka
Provides-Extra: optional
Dynamic: license-file
